ta_lib.libs/libta-lib-5c7e2605.so.0.6.4
talib/__init__.py
talib/_abstract.pxi
talib/_common.pxi
talib/_func.pxi
talib/_stream.pxi
talib/_ta_lib.c
talib/_ta_lib.cpython-312-x86_64-linux-gnu.so
talib/_ta_lib.pxd
talib/_ta_lib.pyi
talib/_ta_lib.pyx
talib/abstract.py
talib/common.pxd
talib/deprecated.py
talib/py.typed
talib/stream.py
ta_lib-0.6.8.dist-info/METADATA
ta_lib-0.6.8.dist-info/WHEEL
ta_lib-0.6.8.dist-info/top_level.txt
ta_lib-0.6.8.dist-info/RECORD
ta_lib-0.6.8.dist-info/licenses/LICENSE
