Metadata-Version: 2.4
Name: TA-Lib
Version: 0.6.8
Summary: Python wrapper for TA-Lib
Author-email: John Benediktsson <mrjbq7@gmail.com>
Project-URL: homepage, http://github.com/ta-lib/ta-lib-python
Project-URL: download, https://github.com/ta-lib/ta-lib-python/releases
Classifier: Development Status :: 5 - Production/Stable
Classifier: Operating System :: Unix
Classifier: Operating System :: POSIX
Classifier: Operating System :: MacOS :: MacOS X
Classifier: Operating System :: Microsoft :: Windows
Classifier: Programming Language :: Python
Classifier: Programming Language :: Python :: 3
Classifier: Programming Language :: Python :: 3.9
Classifier: Programming Language :: Python :: 3.10
Classifier: Programming Language :: Python :: 3.11
Classifier: Programming Language :: Python :: 3.12
Classifier: Programming Language :: Python :: 3.13
Classifier: Programming Language :: Python :: 3.14
Classifier: Programming Language :: Cython
Classifier: Topic :: Office/Business :: Financial
Classifier: Topic :: Scientific/Engineering :: Mathematics
Classifier: Intended Audience :: Developers
Classifier: Intended Audience :: Science/Research
Classifier: Intended Audience :: Financial and Insurance Industry
Requires-Python: >=3.9
License-File: LICENSE
Requires-Dist: build
Requires-Dist: numpy
Dynamic: license-file
